README
setup.py
yolk_portage.py
yolk_portage.egg-info/PKG-INFO
yolk_portage.egg-info/SOURCES.txt
yolk_portage.egg-info/dependency_links.txt
yolk_portage.egg-info/entry_points.txt
yolk_portage.egg-info/top_level.txt
