Metadata-Version: 1.0
Name: yolk-portage
Version: 0.1
Summary: Plugin to show which Python packages were installed via Gentoo's Portage system.
Home-page: http://tools.assembla.com/yolk/
Author: Rob Cakebread
Author-email: gentoodev a t gmail . com
License: GPL-2
Keywords: Gentoo portage PyPI setuptools cheeseshop distutils eggs package management
Platform: UNKNOWN
Classifier: Development Status :: 2 - Pre-Alpha
Classifier: Intended Audience :: Developers
Classifier: Programming Language :: Python
Classifier: Topic :: Software Development :: Libraries :: Python Modules
